MANIFEST.in
README.md
setup.cfg
setup.py
../README.md
deps/bin/beeline
deps/bin/beeline.cmd
deps/bin/docker-image-tool.sh
deps/bin/find-spark-home
deps/bin/find-spark-home.cmd
deps/bin/load-spark-env.cmd
deps/bin/load-spark-env.sh
deps/bin/pyspark
deps/bin/pyspark.cmd
deps/bin/pyspark2.cmd
deps/bin/run-example
deps/bin/run-example.cmd
deps/bin/spark-class
deps/bin/spark-class.cmd
deps/bin/spark-class2.cmd
deps/bin/spark-shell
deps/bin/spark-shell.cmd
deps/bin/spark-shell2.cmd
deps/bin/spark-sql
deps/bin/spark-sql.cmd
deps/bin/spark-sql2.cmd
deps/bin/spark-submit
deps/bin/spark-submit.cmd
deps/bin/spark-submit2.cmd
deps/bin/sparkR
deps/bin/sparkR.cmd
deps/bin/sparkR2.cmd
deps/examples/als.py
deps/examples/avro_inputformat.py
deps/examples/kmeans.py
deps/examples/logistic_regression.py
deps/examples/pagerank.py
deps/examples/parquet_inputformat.py
deps/examples/pi.py
deps/examples/sort.py
deps/examples/status_api_demo.py
deps/examples/transitive_closure.py
deps/examples/wordcount.py
pyspark/__init__.py
pyspark/_globals.py
pyspark/accumulators.py
pyspark/broadcast.py
pyspark/cloudpickle.py
pyspark/conf.py
pyspark/context.py
pyspark/daemon.py
pyspark/files.py
pyspark/find_spark_home.py
pyspark/heapq3.py
pyspark/java_gateway.py
pyspark/join.py
pyspark/profiler.py
pyspark/rdd.py
pyspark/rddsampler.py
pyspark/resource.py
pyspark/resultiterable.py
pyspark/serializers.py
pyspark/shell.py
pyspark/shuffle.py
pyspark/statcounter.py
pyspark/status.py
pyspark/storagelevel.py
pyspark/taskcontext.py
pyspark/traceback_utils.py
pyspark/util.py
pyspark/version.py
pyspark/worker.py
pyspark/ml/__init__.py
pyspark/ml/base.py
pyspark/ml/classification.py
pyspark/ml/clustering.py
pyspark/ml/common.py
pyspark/ml/evaluation.py
pyspark/ml/feature.py
pyspark/ml/fpm.py
pyspark/ml/functions.py
pyspark/ml/image.py
pyspark/ml/pipeline.py
pyspark/ml/recommendation.py
pyspark/ml/regression.py
pyspark/ml/stat.py
pyspark/ml/tree.py
pyspark/ml/tuning.py
pyspark/ml/util.py
pyspark/ml/wrapper.py
pyspark_cloud.egg-info/PKG-INFO
pyspark_cloud.egg-info/SOURCES.txt
pyspark_cloud.egg-info/dependency_links.txt
pyspark_cloud.egg-info/requires.txt
pyspark_cloud.egg-info/top_level.txt