Metadata-Version: 2.1
Name: pyspark-cloud
Version: 0.0.0
Summary: Tekumara build of Apache Spark with Hadoop 3.1
Home-page: https://github.com/tekumara/spark
Author: tekumara
Author-email: tekumara.codes@gmail.com
License: http://www.apache.org/licenses/LICENSE-2.0
Platform: UNKNOWN
Classifier: Development Status :: 5 - Production/Stable
Classifier: License :: OSI Approved :: Apache Software License
Classifier: Programming Language :: Python :: 2.7
Classifier: Programming Language :: Python :: 3
Classifier: Programming Language :: Python :: 3.4
Classifier: Programming Language :: Python :: 3.5
Classifier: Programming Language :: Python :: 3.6
Classifier: Programming Language :: Python :: 3.7
Classifier: Programming Language :: Python :: 3.8
Classifier: Programming Language :: Python :: Implementation :: CPython
Classifier: Programming Language :: Python :: Implementation :: PyPy
Provides-Extra: ml
Provides-Extra: mllib
Provides-Extra: sql
